hepdata_converter/__init__.py
hepdata_converter/common.py
hepdata_converter/version.py
hepdata_converter/parsers/__init__.py
hepdata_converter/parsers/oldhepdata_parser.py
hepdata_converter/parsers/yaml_parser.py
hepdata_converter/testsuite/__init__.py
hepdata_converter/testsuite/test_arraywriter.py
hepdata_converter/testsuite/test_clitools.py
hepdata_converter/testsuite/test_convert.py
hepdata_converter/testsuite/test_csvwriter.py
hepdata_converter/testsuite/test_getconcretesubclassmixin.py
hepdata_converter/testsuite/test_oldhepdata.py
hepdata_converter/testsuite/test_optioninitmixin.py
hepdata_converter/testsuite/test_parser.py
hepdata_converter/testsuite/test_rootwriter.py
hepdata_converter/testsuite/test_writer.py
hepdata_converter/testsuite/test_yamlparser.py
hepdata_converter/testsuite/test_yamlwriter.py
hepdata_converter/testsuite/test_yoda1writer.py
hepdata_converter/testsuite/test_yodawriter.py
hepdata_converter/testsuite/testdata/csv/table_1.csv
hepdata_converter/testsuite/testdata/csv/table_5_noqual.csv
hepdata_converter/testsuite/testdata/csv/table_9.csv
hepdata_converter/testsuite/testdata/csv/table_9_unpacked.csv
hepdata_converter/testsuite/testdata/csv/table_9_unpacked_comma.csv
hepdata_converter/testsuite/testdata/csv/full/Table1.csv
hepdata_converter/testsuite/testdata/csv/full/Table2.csv
hepdata_converter/testsuite/testdata/csv/full/Table3.csv
hepdata_converter/testsuite/testdata/csv/full/Table4.csv
hepdata_converter/testsuite/testdata/csv/full/Table5.csv
hepdata_converter/testsuite/testdata/csv/full/Table6.csv
hepdata_converter/testsuite/testdata/csv/full/Table7.csv
hepdata_converter/testsuite/testdata/csv/full/Table8.csv
hepdata_converter/testsuite/testdata/oldhepdata/1396331.oldhepdata
hepdata_converter/testsuite/testdata/oldhepdata/sample.input
hepdata_converter/testsuite/testdata/oldhepdata/sample.input_single.yaml
hepdata_converter/testsuite/testdata/oldhepdata/1396331-yaml/data1.yaml
hepdata_converter-0.3.3.dist-info/licenses/LICENSE.txt
hepdata_converter-0.3.3.dist-info/METADATA
hepdata_converter-0.3.3.dist-info/WHEEL
hepdata_converter-0.3.3.dist-info/entry_points.txt
hepdata_converter-0.3.3.dist-info/top_level.txt
hepdata_converter-0.3.3.dist-info/RECORD
