Metadata-Version: 2.4
Name: hepdata-converter
Version: 0.3.3
Summary: Library providing means of conversion between oldhepdata format to new one, and new one to csv / yoda / root etc.
Home-page: https://github.com/HEPData/hepdata-converter
Download-URL: https://github.com/HEPData/hepdata-converter/tarball/0.3.3
Author: HEPData Team
Author-email: info@hepdata.net
License: GPL
Requires-Python: >=3.6
License-File: LICENSE.txt
Requires-Dist: hepdata-validator>=0.3.6
Provides-Extra: docs
Requires-Dist: Sphinx>=1.4.2; extra == "docs"
Requires-Dist: mock; extra == "docs"
Provides-Extra: tests
Requires-Dist: coverage>=5.1; extra == "tests"
Dynamic: author
Dynamic: author-email
Dynamic: description
Dynamic: description-content-type
Dynamic: download-url
Dynamic: home-page
Dynamic: license
Dynamic: license-file
Dynamic: provides-extra
Dynamic: requires-dist
Dynamic: requires-python
Dynamic: summary
